vocutil/__init__.py
vocutil-0.0.1.dist-info/LICENSE.rst
vocutil-0.0.1.dist-info/METADATA
vocutil-0.0.1.dist-info/WHEEL
vocutil-0.0.1.dist-info/entry_points.txt
vocutil-0.0.1.dist-info/top_level.txt
vocutil-0.0.1.dist-info/RECORD
