Metadata-Version: 2.1
Name: vocutil
Version: 0.0.1
Summary: Python Conventional Commit Checker
Home-page: https://github.com/jeremyagray/vocutil
Author: Jeremy A Gray
Author-email: gray@flyquackswim.com
Maintainer: Jeremy A Gray
Maintainer-email: gray@flyquackswim.com
License: GPL-3.0-or-later
Project-URL: Issues, https://github.com/jeremyagray/vocutil/issues
Project-URL: Documentation, https://vocutil.readthedocs.io/
Project-URL: Repository, https://github.com/jeremyagray/vocutil
Classifier: Development Status :: 3 - Alpha
Classifier: License :: OSI Approved :: GNU General Public License v3 or later (GPLv3+)
Classifier: Intended Audience :: Education
Classifier: Programming Language :: Python :: 3.8
Classifier: Programming Language :: Python :: 3.9
Classifier: Programming Language :: Python :: 3.10
Classifier: Topic :: Software Development :: Version Control :: Git
License-File: LICENSE.rst
Requires-Dist: pyenchant
Requires-Dist: ruamel.yaml
Requires-Dist: toml
